pytraccar/__init__.py
pytraccar/client.py
pytraccar/exceptions.py
pytraccar/models/__init__.py
pytraccar/models/device.py
pytraccar/models/geofence.py
pytraccar/models/position.py
pytraccar/models/reports_event.py
pytraccar/models/server.py
pytraccar/models/subscription.py
pytraccar/py.typed
pytraccar-3.0.0.dist-info/LICENSE
pytraccar-3.0.0.dist-info/METADATA
pytraccar-3.0.0.dist-info/WHEEL
pytraccar-3.0.0.dist-info/RECORD
