Metadata-Version: 2.3
Name: pytraccar
Version: 3.0.0
Summary: 
License: MIT
Author: Ludeeus
Author-email: joasoe@proton.me
Maintainer: Ludeeus
Maintainer-email: joasoe@proton.me
Requires-Python: >=3.13
Classifier: Intended Audience :: Developers
Classifier: License :: OSI Approved :: MIT License
Classifier: Natural Language :: English
Classifier: Programming Language :: Python :: 3
Classifier: Programming Language :: Python :: 3.13
Classifier: Topic :: Software Development :: Libraries :: Python Modules
Requires-Dist: aiohttp (>=3.6,<4.0)
Project-URL: Bug tracker, https://github.com/ludeeus/pytraccar/issues
Project-URL: Repository, https://github.com/ludeeus/pytraccar
